README
setup.py
Dustbowl.egg-info/PKG-INFO
Dustbowl.egg-info/SOURCES.txt
Dustbowl.egg-info/dependency_links.txt
Dustbowl.egg-info/entry_points.txt
Dustbowl.egg-info/not-zip-safe
Dustbowl.egg-info/requires.txt
Dustbowl.egg-info/top_level.txt
dustbowl/__init__.py
dustbowl/api.py
dustbowl/config.py
dustbowl/env.py
dustbowl/error.py
dustbowl/log.py
dustbowl/shell.py
dustbowl/tabcomp.py
dustbowl/util.py
dustbowl/plugins/__init__.py
dustbowl/plugins/config.py
dustbowl/plugins/datasources.py
dustbowl/plugins/logcmd.py
dustbowl/plugins/modules.py
scripts/dustbowl