Metadata-Version: 1.0
Name: Dustbowl
Version: 1.0.1
Summary: Dustbowl
Home-page: http://pacopablo.github.com/dustbowl
Author: John Hampton
Author-email: pacopablo@pacopablo.com
License: MIT
Platform: UNKNOWN
